{
  "date": "1404/01/24, 15:46",
  "currencies": [
    {
      "code": "btc",
      "name": "بیت کوین",
      "price": 84548.6,
      "icon": "https://alanchand.com/images/logo/crypto/btc.svg",
      "en": "Bitcoin"
    },
    {
      "code": "eth",
      "name": "اتریوم",
      "price": 1604.7199707,
      "icon": "https://alanchand.com/images/logo/crypto/eth.svg",
      "en": "Ethereum"
    },
    {
      "code": "xmr",
      "name": "مونرو",
      "price": 207.16000366,
      "icon": "https://alanchand.com/images/logo/crypto/xmr.svg",
      "en": "Monero"
    },
    {
      "code": "trx",
      "name": "ترون",
      "price": 0.24668001,
      "icon": "https://alanchand.com/images/logo/crypto/trx.svg",
      "en": "Tron"
    },
    {
      "code": "usdt",
      "name": "تتر",
      "price": 86171,
      "icon": "https://alanchand.com/images/logo/crypto/usdt.svg",
      "en": "Tether"
    },
    {
      "code": "bnb",
      "name": "بایننس کوین",
      "price": 587.76000977,
      "icon": "https://alanchand.com/images/logo/crypto/bnb.svg",
      "en": "Binance Coin"
    },
    {
      "code": "ltc",
      "name": "لایت کوین",
      "price": 79.12000275,
      "icon": "https://alanchand.com/images/logo/crypto/ltc.svg",
      "en": "Litecoin"
    },
    {
      "code": "shib",
      "name": "شیبا",
      "price": 0.012299,
      "icon": "https://alanchand.com/images/logo/crypto/shib.svg",
      "en": "Shiba Ino"
    },
    {
      "code": "ada",
      "name": "کاردانو",
      "price": 0.65380001,
      "icon": "https://alanchand.com/images/logo/crypto/ada.svg",
      "en": "Cardano"
    },
    {
      "code": "bch",
      "name": "بیت‌کوین‌کش",
      "price": 347.38000488,
      "icon": "https://alanchand.com/images/logo/crypto/bch.svg",
      "en": "Bitcoin Cash"
    },
    {
      "code": "dai",
      "name": "دای",
      "price": 86573,
      "icon": "https://alanchand.com/images/logo/crypto/dai.svg",
      "en": "Dai"
    },
    {
      "code": "etc",
      "name": "اتریوم کلاسیک",
      "price": 15.2869997,
      "icon": "https://alanchand.com/images/logo/crypto/etc.svg",
      "en": "Eth Classic"
    },
    {
      "code": "uni",
      "name": "یونی‌سواپ",
      "price": 5.42600012,
      "icon": "https://alanchand.com/images/logo/crypto/uni.svg",
      "en": "Uniswap"
    },
    {
      "code": "doge",
      "name": "دوج‌کوین",
      "price": 0.16531999,
      "icon": "https://alanchand.com/images/logo/crypto/doge.svg",
      "en": "Dogecoin"
    },
    {
      "code": "link",
      "name": "چین‌لینک",
      "price": 12.86299992,
      "icon": "https://alanchand.com/images/logo/crypto/link.svg",
      "en": "Chainlink"
    }
  ]
}