{
  "date": "1404/01/29, 08:05",
  "currencies": [
    {
      "code": "usd",
      "name": "دلار آمریکا",
      "price": 85600,
      "icon": "https://raw.githubusercontent.com/HatScripts/circle-flags/refs/heads/gh-pages/flags/us.svg",
      "en": "US Dollar"
    },
    {
      "code": "eur",
      "name": "یورو",
      "price": 97350,
      "icon": "https://raw.githubusercontent.com/HatScripts/circle-flags/refs/heads/gh-pages/flags/european_union.svg",
      "en": "Euro"
    },
    {
      "code": "try",
      "name": "لیر ترکیه",
      "price": 2280,
      "icon": "https://raw.githubusercontent.com/HatScripts/circle-flags/refs/heads/gh-pages/flags/tr.svg",
      "en": "Turkish Lira"
    },
    {
      "code": "gbp",
      "name": "پوند انگلستان",
      "price": 112550,
      "icon": "https://raw.githubusercontent.com/HatScripts/circle-flags/refs/heads/gh-pages/flags/gb.svg",
      "en": "British Pound"
    },
    {
      "code": "aed",
      "name": "درهم امارات",
      "price": 23450,
      "icon": "https://raw.githubusercontent.com/HatScripts/circle-flags/refs/heads/gh-pages/flags/ae.svg",
      "en": "UAE Dirham"
    },
    {
      "code": "cad",
      "name": "دلار کانادا",
      "price": 61850,
      "icon": "https://raw.githubusercontent.com/HatScripts/circle-flags/refs/heads/gh-pages/flags/ca.svg",
      "en": "Canadian Dollar"
    },
    {
      "code": "cny",
      "name": "یوان چین",
      "price": 11820,
      "icon": "https://raw.githubusercontent.com/HatScripts/circle-flags/refs/heads/gh-pages/flags/cn.svg",
      "en": "Chinese Yuan"
    },
    {
      "code": "aud",
      "name": "دلار استرالیا",
      "price": 54650,
      "icon": "https://raw.githubusercontent.com/HatScripts/circle-flags/refs/heads/gh-pages/flags/au.svg",
      "en": "Australian Dollar"
    },
    {
      "code": "myr",
      "name": "رینگیت مالزی",
      "price": 19450,
      "icon": "https://raw.githubusercontent.com/HatScripts/circle-flags/refs/heads/gh-pages/flags/my.svg",
      "en": "Malaysian Ringgit"
    },
    {
      "code": "rub",
      "name": "روبل روسیه",
      "price": 1040,
      "icon": "https://raw.githubusercontent.com/HatScripts/circle-flags/refs/heads/gh-pages/flags/ru.svg",
      "en": "Russian Ruble"
    },
    {
      "code": "iqd",
      "name": "دینار عراق",
      "price": 5590,
      "icon": "https://raw.githubusercontent.com/HatScripts/circle-flags/refs/heads/gh-pages/flags/iq.svg",
      "en": "Iraqi Dinar"
    },
    {
      "code": "sek",
      "name": "کرون سوئد",
      "price": 8900,
      "icon": "https://raw.githubusercontent.com/HatScripts/circle-flags/refs/heads/gh-pages/flags/se.svg",
      "en": "Swedish Krona"
    },
    {
      "code": "thb",
      "name": "بات تایلند",
      "price": 2570,
      "icon": "https://raw.githubusercontent.com/HatScripts/circle-flags/refs/heads/gh-pages/flags/th.svg",
      "en": "Thai Baht"
    },
    {
      "code": "amd",
      "name": "درام ارمنستان",
      "price": 21910,
      "icon": "https://raw.githubusercontent.com/HatScripts/circle-flags/refs/heads/gh-pages/flags/am.svg",
      "en": "Armenian Dram"
    },
    {
      "code": "azn",
      "name": "مانات آذربایجان",
      "price": 50400,
      "icon": "https://raw.githubusercontent.com/HatScripts/circle-flags/refs/heads/gh-pages/flags/az.svg",
      "en": "Azerbaijani Manat"
    },
    {
      "code": "gel",
      "name": "لاری گرجستان",
      "price": 31190,
      "icon": "https://raw.githubusercontent.com/HatScripts/circle-flags/refs/heads/gh-pages/flags/ge.svg",
      "en": "Georgian Lari"
    },
    {
      "code": "sar",
      "name": "ریال عربستان",
      "price": 22870,
      "icon": "https://raw.githubusercontent.com/HatScripts/circle-flags/refs/heads/gh-pages/flags/sa.svg",
      "en": "Saudi Riyal"
    },
    {
      "code": "inr",
      "name": "روپیه هندوستان",
      "price": 1005,
      "icon": "https://raw.githubusercontent.com/HatScripts/circle-flags/refs/heads/gh-pages/flags/in.svg",
      "en": "Indian Rupee"
    },
    {
      "code": "jpy",
      "name": "ین ژاپن",
      "price": 60250,
      "icon": "https://raw.githubusercontent.com/HatScripts/circle-flags/refs/heads/gh-pages/flags/jp.svg",
      "en": "Japanese Yen"
    },
    {
      "code": "chf",
      "name": "فرانک سوئیس",
      "price": 104850,
      "icon": "https://raw.githubusercontent.com/HatScripts/circle-flags/refs/heads/gh-pages/flags/ch.svg",
      "en": "Swiss Franc"
    },
    {
      "code": "afn",
      "name": "افغانی افغانستان",
      "price": 1185,
      "icon": "https://raw.githubusercontent.com/HatScripts/circle-flags/refs/heads/gh-pages/flags/af.svg",
      "en": "Afghani"
    },
    {
      "code": "sgd",
      "name": "دلار سنگاپور",
      "price": 65350,
      "icon": "https://raw.githubusercontent.com/HatScripts/circle-flags/refs/heads/gh-pages/flags/sg.svg",
      "en": "Singapore Dollar"
    },
    {
      "code": "brl",
      "name": "رئال برزیل",
      "price": 14610,
      "icon": "https://raw.githubusercontent.com/HatScripts/circle-flags/refs/heads/gh-pages/flags/br.svg",
      "en": "Brazilian Real"
    },
    {
      "code": "dkk",
      "name": "کرون دانمارک",
      "price": 13070,
      "icon": "https://raw.githubusercontent.com/HatScripts/circle-flags/refs/heads/gh-pages/flags/dk.svg",
      "en": "Danish Krone"
    },
    {
      "code": "kwd",
      "name": "دینار کویت",
      "price": 279550,
      "icon": "https://raw.githubusercontent.com/HatScripts/circle-flags/refs/heads/gh-pages/flags/kw.svg",
      "en": "Kuwaiti Dinar"
    },
    {
      "code": "nok",
      "name": "کرون نروژ",
      "price": 8180,
      "icon": "https://raw.githubusercontent.com/HatScripts/circle-flags/refs/heads/gh-pages/flags/no.svg",
      "en": "Norwegian Krone"
    },
    {
      "code": "nzd",
      "name": "دلار نیوزلند",
      "price": 50900,
      "icon": "https://raw.githubusercontent.com/HatScripts/circle-flags/refs/heads/gh-pages/flags/nz.svg",
      "en": "New Zealand Dollar"
    },
    {
      "code": "omr",
      "name": "ریال عمان",
      "price": 223000,
      "icon": "https://raw.githubusercontent.com/HatScripts/circle-flags/refs/heads/gh-pages/flags/om.svg",
      "en": "Omani Rial"
    },
    {
      "code": "pkr",
      "name": "روپیه پاکستان",
      "price": 305,
      "icon": "https://raw.githubusercontent.com/HatScripts/circle-flags/refs/heads/gh-pages/flags/pk.svg",
      "en": "Pakistani Rupee"
    },
    {
      "code": "ars",
      "name": "پزو آرژانتین",
      "price": 73,
      "icon": "https://raw.githubusercontent.com/HatScripts/circle-flags/refs/heads/gh-pages/flags/ar.svg",
      "en": "Argentine Peso"
    },
    {
      "code": "bhd",
      "name": "دینار بحرین",
      "price": 228050,
      "icon": "https://raw.githubusercontent.com/HatScripts/circle-flags/refs/heads/gh-pages/flags/bh.svg",
      "en": "Bhutanese Ngultrum"
    },
    {
      "code": "krw",
      "name": "وون کره جنوبی",
      "price": 6050,
      "icon": "https://raw.githubusercontent.com/HatScripts/circle-flags/refs/heads/gh-pages/flags/kr.svg",
      "en": "Korean Won"
    },
    {
      "code": "syp",
      "name": "پوند سوریه",
      "price": 664,
      "icon": "https://raw.githubusercontent.com/HatScripts/circle-flags/refs/heads/gh-pages/flags/sy.svg",
      "en": "Syrian Pound"
    },
    {
      "code": "qar",
      "name": "ریال قطر",
      "price": 23560,
      "icon": "https://raw.githubusercontent.com/HatScripts/circle-flags/refs/heads/gh-pages/flags/qa.svg",
      "en": "Qatari Riyal"
    },
    {
      "code": "hkd",
      "name": "دلار هنگ کنگ",
      "price": 11050,
      "icon": "https://raw.githubusercontent.com/HatScripts/circle-flags/refs/heads/gh-pages/flags/hk.svg",
      "en": "Hong Kong Dollar"
    },
    {
      "code": "kgs",
      "name": "سوم قرقیزستان",
      "price": 980,
      "icon": "https://raw.githubusercontent.com/HatScripts/circle-flags/refs/heads/gh-pages/flags/kg.svg",
      "en": "Kyrgyzstani Som"
    },
    {
      "code": "tjs",
      "name": "سامانی تاجیکستان",
      "price": 7890,
      "icon": "https://raw.githubusercontent.com/HatScripts/circle-flags/refs/heads/gh-pages/flags/tj.svg",
      "en": "Tajikistani Somoni"
    },
    {
      "code": "tmt",
      "name": "منات ترکمنستان",
      "price": 24490,
      "icon": "https://raw.githubusercontent.com/HatScripts/circle-flags/refs/heads/gh-pages/flags/tm.svg",
      "en": "Turkmen Manat"
    },
    {
      "code": "abshodeh",
      "name": "مثقال طلا",
      "price": 29720000,
      "icon": "https://platform.tgju.org/files/images/gold-bar-1622253729.png",
      "en": "Mithqal"
    },
    {
      "code": "18ayar",
      "name": "طلا 18 عیار",
      "price": 6859970,
      "icon": "https://platform.tgju.org/files/images/gold-bar-1-1622253841.png",
      "en": "18 Karat"
    },
    {
      "code": "sekkeh",
      "name": "سکه امامی",
      "price": 79100000,
      "icon": "https://platform.tgju.org/files/images/gold-1697963730.png",
      "en": "Emami"
    },
    {
      "code": "bahar",
      "name": "سکه بهار آزادی",
      "price": 73800000,
      "icon": "https://platform.tgju.org/files/images/gold-1-1697963918.png",
      "en": "Bahar Azadi"
    },
    {
      "code": "nim",
      "name": "نیم سکه",
      "price": 49300000,
      "icon": "https://platform.tgju.org/files/images/money-1697964123.png",
      "en": "Half Coin"
    },
    {
      "code": "rob",
      "name": "ربع سکه",
      "price": 27500000,
      "icon": "https://platform.tgju.org/files/images/revenue-1697964369.png",
      "en": "Quarter Coin"
    },
    {
      "code": "gram",
      "name": "سکه گرمی",
      "price": 8850000,
      "icon": "https://platform.tgju.org/files/images/parsian-coin-1697964860.png",
      "en": "Gram Coin"
    },
    {
      "code": "usd_xau",
      "name": "انس طلا",
      "price": 3315.12,
      "icon": "https://platform.tgju.org/files/images/gold-1-1622253769.png",
      "en": "USD Gold"
    },
    {
      "code": "btc",
      "name": "بیت کوین",
      "price": 84647.4,
      "icon": "https://alanchand.com/images/logo/crypto/btc.svg",
      "en": "Bitcoin"
    },
    {
      "code": "eth",
      "name": "اتریوم",
      "price": 1582,
      "icon": "https://alanchand.com/images/logo/crypto/eth.svg",
      "en": "Ethereum"
    },
    {
      "code": "xmr",
      "name": "مونرو",
      "price": 216.16000366,
      "icon": "https://alanchand.com/images/logo/crypto/xmr.svg",
      "en": "Monero"
    },
    {
      "code": "trx",
      "name": "ترون",
      "price": 0.24559,
      "icon": "https://alanchand.com/images/logo/crypto/trx.svg",
      "en": "Tron"
    },
    {
      "code": "usdt",
      "name": "تتر",
      "price": 85471,
      "icon": "https://alanchand.com/images/logo/crypto/usdt.svg",
      "en": "Tether"
    },
    {
      "code": "bnb",
      "name": "بایننس کوین",
      "price": 589.09997559,
      "icon": "https://alanchand.com/images/logo/crypto/bnb.svg",
      "en": "Binance Coin"
    },
    {
      "code": "ltc",
      "name": "لایت کوین",
      "price": 75.36000061,
      "icon": "https://alanchand.com/images/logo/crypto/ltc.svg",
      "en": "Litecoin"
    },
    {
      "code": "shib",
      "name": "شیبا",
      "price": 0.011792,
      "icon": "https://alanchand.com/images/logo/crypto/shib.svg",
      "en": "Shiba Ino"
    },
    {
      "code": "ada",
      "name": "کاردانو",
      "price": 0.6128,
      "icon": "https://alanchand.com/images/logo/crypto/ada.svg",
      "en": "Cardano"
    },
    {
      "code": "bch",
      "name": "بیت‌کوین‌کش",
      "price": 328.55999756,
      "icon": "https://alanchand.com/images/logo/crypto/bch.svg",
      "en": "Bitcoin Cash"
    },
    {
      "code": "dai",
      "name": "دای",
      "price": 86111,
      "icon": "https://alanchand.com/images/logo/crypto/dai.svg",
      "en": "Dai"
    },
    {
      "code": "etc",
      "name": "اتریوم کلاسیک",
      "price": 15.19400024,
      "icon": "https://alanchand.com/images/logo/crypto/etc.svg",
      "en": "Eth Classic"
    },
    {
      "code": "uni",
      "name": "یونی‌سواپ",
      "price": 5.17000008,
      "icon": "https://alanchand.com/images/logo/crypto/uni.svg",
      "en": "Uniswap"
    },
    {
      "code": "doge",
      "name": "دوج‌کوین",
      "price": 0.15494999,
      "icon": "https://alanchand.com/images/logo/crypto/doge.svg",
      "en": "Dogecoin"
    },
    {
      "code": "link",
      "name": "چین‌لینک",
      "price": 12.59799957,
      "icon": "https://alanchand.com/images/logo/crypto/link.svg",
      "en": "Chainlink"
    }
  ]
}